main.py
voa_cli-1.0.1.dist-info/METADATA
voa_cli-1.0.1.dist-info/WHEEL
voa_cli-1.0.1.dist-info/entry_points.txt
voa_cli-1.0.1.dist-info/top_level.txt
voa_cli-1.0.1.dist-info/RECORD
