Metadata-Version: 2.4
Name: voa-cli
Version: 1.0.1
Summary: Internal Secret Manager CLI
Requires-Python: >=3.8
Requires-Dist: click
Requires-Dist: requests
